{"nodes": [{"degree": 1.0, "classification": "CONFIDENTIAL", "constraint": 1.0, "color": "hsl(98,94%,53%)", "timestamp": 1230750000.0, "id": "n182895", "missing": 0.0, "uri": "https://wikileaks.org/cable/2008/12/08BRASILIA1684.html", "authority": 0.0, "label": "08BRASILIA1684", "caption": "", "betweenness": 0.0, "pagerank": 2.37049e-06, "place": "BRASILIA", "multilevel": 8.0, "date": "2008-12-31", "colorindex": 1, "subjects": "EMBASSY BRASILIA PROPOSAL FOR S/CT NADR PROJECT", "nodeclass": "CONFIDENTIAL"}, {"degree": 1.0, "classification": "UNCLASSIFIED", "constraint": 1.0, "color": "hsl(157,92%,70%)", "timestamp": 1230020000.0, "id": "n204781", "missing": 0.0, "uri": "https://wikileaks.org/cable/2008/12/08NAIROBI2862.html", "authority": 0.0, "label": "08NAIROBI2862", "caption": "", "betweenness": 0.0, "pagerank": 2.37049e-06, "place": "NAIROBI", "multilevel": 8.0, "date": "2008-12-23", "colorindex": 9, "subjects": "NADR-FUNDED PROJECT TO SUPPORT THE EAST AFRICA REGIONAL STRATEGIC INITIATIVE, PROPOSAL", "nodeclass": "UNCLASSIFIED"}, {"degree": 1.0, "classification": "UNCLASSIFIED", "constraint": 1.0, "color": "hsl(157,92%,70%)", "timestamp": 1230020000.0, "id": "n204784", "missing": 0.0, "uri": "https://wikileaks.org/cable/2008/12/08NAIROBI2867.html", "authority": 0.0, "label": "08NAIROBI2867", "caption": "", "betweenness": 0.0, "pagerank": 2.37049e-06, "place": "NAIROBI", "multilevel": 8.0, "date": "2008-12-23", "colorindex": 9, "subjects": "NADR-FUNDED PROPOSAL FOR INTERNATIONAL PORT SECURITY PROGRAM", "nodeclass": "UNCLASSIFIED"}, {"degree": 1.0, "classification": "SECRET", "constraint": 1.0, "color": "hsl(274,62%,86%)", "timestamp": 1225460000.0, "id": "n205534", "missing": 0.0, "uri": "https://wikileaks.org/cable/2008/10/08NEWDELHI2830.html", "authority": 0.0, "label": "08NEWDELHI2830", "caption": "", "betweenness": 0.0, "pagerank": 2.32925e-06, "place": "NEWDELHI", "multilevel": 8.0, "date": "2008-10-31", "colorindex": 8, "subjects": "REGIONAL SECURITY INITIATIVE: DEVELOPING A SOUTH ASIA COUNTERTERRORISM STRATEGY", "nodeclass": "SECRET"}, {"degree": 1.0, "classification": "SECRET", "constraint": 1.0, "color": "hsl(28,89%,50%)", "timestamp": 1229680000.0, "id": "n211128", "missing": 0.0, "uri": "https://wikileaks.org/cable/2008/12/08ROME1541.html", "authority": 0.0, "label": "08ROME1541", "caption": "", "betweenness": 0.0, "pagerank": 2.37049e-06, "place": "ROME", "multilevel": 8.0, "date": "2008-12-19", "colorindex": 5, "subjects": "REQUEST FOR CRISIS MANAGEMENT TRAINING FOR VATICAN", "nodeclass": "SECRET"}, {"degree": 10.0, "classification": "UNCLASSIFIED", "constraint": 0.1, "color": "hsl(224,92%,96%)", "timestamp": 1228510000.0, "id": "n216426", "missing": 0.0, "uri": "https://wikileaks.org/cable/2008/12/08STATE128554.html", "authority": 0.0, "label": "08STATE128554", "caption": "(NOTAL)", "betweenness": 0.000179915, "pagerank": 2.04635e-05, "place": "STATE", "multilevel": 8.0, "date": "2008-12-05", "colorindex": 4, "subjects": "S/CT:  SOLICITATION FOR NADR-FUNDED PROPOSALS TO SUPPORT THE REGIONAL STRATEGIC INITIATIVES", "nodeclass": "UNCLASSIFIED"}, {"degree": 1.0, "classification": "UNCLASSIFIED//FOR OFFICIAL USE ONLY", "constraint": 1.0, "color": "hsl(321,52%,86%)", "timestamp": 1235060000.0, "id": "n231243", "missing": 0.0, "uri": "https://wikileaks.org/cable/2009/02/09AMMAN470.html", "authority": 0.0, "label": "09AMMAN470", "caption": "", "betweenness": 0.0, "pagerank": 2.37049e-06, "place": "AMMAN", "multilevel": 8.0, "date": "2009-02-19", "colorindex": 6, "subjects": "PROPOSALS FOR NADR-FUNDED PROGRAMS TO SUPPORT RSI GOALS IN JORDAN", "nodeclass": "UNCLASSIFIED-FOR-OFFICIAL-USE-ONLY"}, {"degree": 1.0, "classification": "UNCLASSIFIED//FOR OFFICIAL USE ONLY", "constraint": 1.0, "color": "hsl(80,91%,58%)", "timestamp": 1235130000.0, "id": "n231901", "missing": 0.0, "uri": "https://wikileaks.org/cable/2009/02/09ANKARA269.html", "authority": 0.0, "label": "09ANKARA269", "caption": "", "betweenness": 0.0, "pagerank": 2.37049e-06, "place": "ANKARA", "multilevel": 8.0, "date": "2009-02-20", "colorindex": 3, "subjects": "TURKEY: PROPOSAL FOR NADR-FUNDED COUNTER-NARCO-TERRORISM PROJECT", "nodeclass": "UNCLASSIFIED-FOR-OFFICIAL-USE-ONLY"}, {"degree": 3.0, "classification": "CONFIDENTIAL", "constraint": 0.333333, "color": "hsl(187,57%,98%)", "timestamp": 1231920000.0, "id": "n247995", "missing": 0.0, "uri": "https://wikileaks.org/cable/2009/01/09DHAKA57.html", "authority": 0.0, "label": "09DHAKA57", "caption": "", "betweenness": 0.000219885, "pagerank": 5.99349e-06, "place": "DHAKA", "multilevel": 8.0, "date": "2009-01-14", "colorindex": 0, "subjects": "INDIAN HIGH COMMISSIONER EXPECTS CLOSER COUNTERTERRORISM COOPERATION WITH NEW BANGLADESH GOVERNMENT", "nodeclass": "CONFIDENTIAL"}, {"degree": 1.0, "classification": "UNCLASSIFIED//FOR OFFICIAL USE ONLY", "constraint": 1.0, "color": "hsl(187,57%,98%)", "timestamp": 1232020000.0, "id": "n248035", "missing": 0.0, "uri": "https://wikileaks.org/cable/2009/01/09DHAKA64.html", "authority": 0.0, "label": "09DHAKA64", "caption": "", "betweenness": 0.0, "pagerank": 2.37049e-06, "place": "DHAKA", "multilevel": 8.0, "date": "2009-01-15", "colorindex": 0, "subjects": "PROPOSAL FOR NADR-FUNDED SOUTH ASIA SECURITY DIALOGUE", "nodeclass": "UNCLASSIFIED-FOR-OFFICIAL-USE-ONLY"}, {"degree": 1.0, "classification": "UNCLASSIFIED", "constraint": 1.0, "color": "hsl(176,89%,60%)", "timestamp": 1231240000.0, "id": "n248303", "missing": 0.0, "uri": "https://wikileaks.org/cable/2009/01/09DJIBOUTI10.html", "authority": 0.0, "label": "09DJIBOUTI10", "caption": "", "betweenness": 0.0, "pagerank": 2.37049e-06, "place": "DJIBOUTI", "multilevel": 8.0, "date": "2009-01-06", "colorindex": 2, "subjects": "NADR-FUNDED PROPOSAL TO SUPPORT THE REGIONAL STRATEGIC INITIATIVE", "nodeclass": "UNCLASSIFIED"}, {"degree": 1.0, "classification": "UNCLASSIFIED//FOR OFFICIAL USE ONLY", "constraint": 1.0, "color": "hsl(185,55%,79%)", "timestamp": 1231230000.0, "id": "n253461", "missing": 0.0, "uri": "https://wikileaks.org/cable/2009/01/09JAKARTA18.html", "authority": 0.0, "label": "09JAKARTA18", "caption": "", "betweenness": 0.0, "pagerank": 2.37049e-06, "place": "JAKARTA", "multilevel": 8.0, "date": "2009-01-06", "colorindex": 7, "subjects": "REGIONAL SECURITY INITIATIVE -- MALACCA/SULAWESI RADAR SYSTEMS PROPOSAL", "nodeclass": "UNCLASSIFIED-FOR-OFFICIAL-USE-ONLY"}], "links": [{"duration": 2236200.0, "source": 0, "betweenness": 11.0, "target": 5}, {"duration": 1503960.0, "source": 1, "betweenness": 11.0, "target": 5}, {"duration": 1507620.0, "source": 2, "betweenness": 11.0, "target": 5}, {"duration": 6462000.0, "source": 8, "betweenness": 11.0, "target": 3}, {"duration": 1162320.0, "source": 4, "betweenness": 11.0, "target": 5}, {"duration": 6540720.0, "source": 6, "betweenness": 11.0, "target": 5}, {"duration": 6615780.0, "source": 7, "betweenness": 11.0, "target": 5}, {"duration": 3406260.0, "source": 8, "betweenness": 20.0, "target": 5}, {"duration": 3504360.0, "source": 9, "betweenness": 11.0, "target": 5}, {"duration": 2728620.0, "source": 10, "betweenness": 11.0, "target": 5}, {"duration": 2718120.0, "source": 11, "betweenness": 11.0, "target": 5}]}