{"nodes": [{"degree": 1.0, "classification": "", "missing": 1.0, "color": "hsl(99,67%,26%)", "timestamp": 0.0, "id": "n14205", "constraint": 1.0, "uri": "", "authority": 0.0, "label": "03SECSTATE272314", "caption": "", "betweenness": 0.0, "pagerank": 2.95248e-06, "place": "SECSTATE", "date": null, "colorindex": 0, "subjects": "", "nodeclass": "MISSING"}, {"degree": 2.0, "classification": "UNCLASSIFIED", "missing": 0.0, "color": "hsl(307,54%,30%)", "timestamp": 1064930000.0, "id": "n15759", "constraint": 0.5, "uri": "https://wikileaks.org/cable/2003/09/03THEHAGUE2476.html", "authority": 0.0, "label": "03THEHAGUE2476", "caption": "", "betweenness": 2.0, "pagerank": 5.46209e-06, "place": "THEHAGUE", "date": "2003-09-30", "colorindex": 1, "subjects": "DUTCH CONTRIBUTIONS FOR RECONSTRUCTION OF IRAQI POLICE", "nodeclass": "UNCLASSIFIED"}, {"degree": 1.0, "classification": "", "missing": 1.0, "color": "hsl(99,67%,26%)", "timestamp": 0.0, "id": "n28557", "constraint": 1.0, "uri": "", "authority": 0.0, "label": "04SECSTATE58021", "caption": "", "betweenness": 0.0, "pagerank": 2.95248e-06, "place": "SECSTATE", "date": null, "colorindex": 0, "subjects": "", "nodeclass": "MISSING"}, {"degree": 2.0, "classification": "CONFIDENTIAL", "missing": 0.0, "color": "hsl(307,54%,30%)", "timestamp": 1080910000.0, "id": "n31482", "constraint": 0.5, "uri": "https://wikileaks.org/cable/2004/04/04THEHAGUE867.html", "authority": 0.0, "label": "04THEHAGUE867", "caption": "", "betweenness": 2.0, "pagerank": 5.46209e-06, "place": "THEHAGUE", "date": "2004-04-02", "colorindex": 1, "subjects": "DUTCH TO CONTINUE POLICE TRAINING IN SOUTHERN IRAQ", "nodeclass": "CONFIDENTIAL"}], "links": [{"duration": 0.0, "source": 1, "betweenness": 3.0, "target": 0}, {"duration": 15982700.0, "source": 3, "betweenness": 4.0, "target": 1}, {"duration": 0.0, "source": 3, "betweenness": 3.0, "target": 2}]}