{"nodes": [{"degree": 3.0, "classification": "CONFIDENTIAL", "constraint": 0.333333, "color": "hsl(185,30%,54%)", "timestamp": 1193630000.0, "id": "n136944", "missing": 0.0, "uri": "https://wikileaks.org/cable/2007/10/07JAKARTA3008.html", "authority": 0.0, "label": "07JAKARTA3008", "caption": "", "betweenness": 0.00033897, "pagerank": 4.48486e-06, "place": "JAKARTA", "multilevel": 7.0, "date": "2007-10-29", "colorindex": 0, "subjects": "INDONESIA/TIMOR LESTE -- FINAL COMMISSION REPORT DUE EARLY 2008", "nodeclass": "CONFIDENTIAL"}, {"degree": 3.0, "classification": "CONFIDENTIAL", "constraint": 0.333333, "color": "hsl(185,30%,54%)", "timestamp": 1195640000.0, "id": "n137040", "missing": 0.0, "uri": "https://wikileaks.org/cable/2007/11/07JAKARTA3223.html", "authority": 0.0, "label": "07JAKARTA3223", "caption": "", "betweenness": 0.000139933, "pagerank": 4.64264e-06, "place": "JAKARTA", "multilevel": 7.0, "date": "2007-11-21", "colorindex": 0, "subjects": "INDONESIA REACTS TO REPORT ON JOURNALIST KILLINGS", "nodeclass": "CONFIDENTIAL"}, {"degree": 3.0, "classification": "CONFIDENTIAL", "constraint": 0.40747, "color": "hsl(185,30%,54%)", "timestamp": 1197000000.0, "id": "n137095", "missing": 0.0, "uri": "https://wikileaks.org/cable/2007/12/07JAKARTA3339.html", "authority": 0.0, "label": "07JAKARTA3339", "caption": "", "betweenness": 8.07845e-05, "pagerank": 4.03854e-06, "place": "JAKARTA", "multilevel": 7.0, "date": "2007-12-07", "colorindex": 0, "subjects": "EAST TIMOR -- FINDINGS OF FINAL COMMISSION REPORT COME INTO SOME FOCUS", "nodeclass": "CONFIDENTIAL"}, {"degree": 2.0, "classification": "CONFIDENTIAL", "constraint": 0.5, "color": "hsl(64,27%,74%)", "timestamp": 1216030000.0, "id": "n188441", "missing": 0.0, "uri": "https://wikileaks.org/cable/2008/07/08DILI183.html", "authority": 0.0, "label": "08DILI183", "caption": "", "betweenness": 9.21025e-06, "pagerank": 3.24382e-06, "place": "DILI", "multilevel": 7.0, "date": "2008-07-14", "colorindex": 1, "subjects": "JOSE RAMOS-HORTA PREVIEWS CTF REPORT", "nodeclass": "CONFIDENTIAL"}, {"degree": 3.0, "classification": "CONFIDENTIAL", "constraint": 0.40747, "color": "hsl(185,30%,54%)", "timestamp": 1215680000.0, "id": "n192818", "missing": 0.0, "uri": "https://wikileaks.org/cable/2008/07/08JAKARTA1328.html", "authority": 0.0, "label": "08JAKARTA1328", "caption": "", "betweenness": 4.89995e-05, "pagerank": 3.87121e-06, "place": "JAKARTA", "multilevel": 7.0, "date": "2008-07-10", "colorindex": 0, "subjects": "PLAN FOR LEADERS TO RECEIVE TIMOR-LESTE/INDONESIA COMMISSION REPORT", "nodeclass": "CONFIDENTIAL"}, {"degree": 4.0, "classification": "CONFIDENTIAL", "constraint": 0.5, "color": "hsl(185,30%,54%)", "timestamp": 1216100000.0, "id": "n192829", "missing": 0.0, "uri": "https://wikileaks.org/cable/2008/07/08JAKARTA1351.html", "authority": 0.0, "label": "08JAKARTA1351", "caption": "", "betweenness": 2.90092e-05, "pagerank": 5.40271e-06, "place": "JAKARTA", "multilevel": 7.0, "date": "2008-07-15", "colorindex": 0, "subjects": "TIMOR-LESTE:  LEADERS RECEIVE REPORT OUTLINING HUMAN RIGHTS ABUSES", "nodeclass": "CONFIDENTIAL"}, {"degree": 3.0, "classification": "CONFIDENTIAL", "constraint": 0.333333, "color": "hsl(185,30%,54%)", "timestamp": 1216370000.0, "id": "n192844", "missing": 0.0, "uri": "https://wikileaks.org/cable/2008/07/08JAKARTA1385.html", "authority": 0.0, "label": "08JAKARTA1385", "caption": "", "betweenness": 3.09638e-05, "pagerank": 5.07006e-06, "place": "JAKARTA", "multilevel": 7.0, "date": "2008-07-18", "colorindex": 0, "subjects": "GOI ACCEPTS RESPONSIBILITY FORHQUMAN RIGHTS VIOLATIONS IN EAST TIMOR", "nodeclass": "CONFIDENTIAL"}, {"degree": 2.0, "classification": "CONFIDENTIAL", "constraint": 0.5, "color": "hsl(185,30%,54%)", "timestamp": 1216810000.0, "id": "n192858", "missing": 0.0, "uri": "https://wikileaks.org/cable/2008/07/08JAKARTA1416.html", "authority": 0.0, "label": "08JAKARTA1416", "caption": "", "betweenness": 1.92006e-07, "pagerank": 3.44623e-06, "place": "JAKARTA", "multilevel": 7.0, "date": "2008-07-23", "colorindex": 0, "subjects": "TIMOR-LESTE: HUMAN RIGHTS ACTIVISTS PRAISE--AND CRITICIZE--COMMISSION REPORT", "nodeclass": "CONFIDENTIAL"}, {"degree": 1.0, "classification": "CONFIDENTIAL", "constraint": 1.0, "color": "hsl(185,30%,54%)", "timestamp": 1219400000.0, "id": "n192940", "missing": 0.0, "uri": "https://wikileaks.org/cable/2008/08/08JAKARTA1596.html", "authority": 0.0, "label": "08JAKARTA1596", "caption": "", "betweenness": 0.0, "pagerank": 2.06761e-06, "place": "JAKARTA", "multilevel": 7.0, "date": "2008-08-22", "colorindex": 0, "subjects": "CONGRESSIONAL FELLOW REVIEWS TREATMENT OF MINORITY SECT", "nodeclass": "CONFIDENTIAL"}, {"degree": 7.0, "classification": "CONFIDENTIAL", "constraint": 0.271117, "color": "hsl(185,30%,54%)", "timestamp": 1201260000.0, "id": "n192955", "missing": 0.0, "uri": "https://wikileaks.org/cable/2008/01/08JAKARTA163.html", "authority": 0.0, "label": "08JAKARTA163", "caption": "", "betweenness": 0.000951828, "pagerank": 8.63093e-06, "place": "JAKARTA", "multilevel": 7.0, "date": "2008-01-25", "colorindex": 0, "subjects": "EAST TIMOR/INDONESIA -- KEY EXPERT PREVIEWS JOINT COMMISSION REPORT", "nodeclass": "CONFIDENTIAL"}, {"degree": 1.0, "classification": "", "constraint": 1.0, "color": "hsl(185,30%,54%)", "timestamp": 1220940000.0, "id": "n192989", "missing": 1.0, "uri": "", "authority": 0.0, "label": "08JAKARTA1700", "caption": "", "betweenness": 0.0, "pagerank": 1.84795e-06, "place": "JAKARTA", "multilevel": 7.0, "date": "2008-09-09", "colorindex": 0, "subjects": "", "nodeclass": "MISSING"}, {"degree": 2.0, "classification": "CONFIDENTIAL", "constraint": 0.902778, "color": "hsl(185,30%,54%)", "timestamp": 1224150000.0, "id": "n193090", "missing": 0.0, "uri": "https://wikileaks.org/cable/2008/10/08JAKARTA1924.html", "authority": 0.0, "label": "08JAKARTA1924", "caption": "", "betweenness": 0.0, "pagerank": 3.21382e-06, "place": "JAKARTA", "multilevel": 7.0, "date": "2008-10-16", "colorindex": 0, "subjects": "PRESIDENT UNDERSCORES CONTINUED NEED FOR THE MILITARY'S NEUTRALITY IN POLITICS", "nodeclass": "CONFIDENTIAL"}, {"degree": 6.0, "classification": "CONFIDENTIAL", "constraint": 0.236111, "color": "hsl(185,30%,54%)", "timestamp": 1224480000.0, "id": "n193094", "missing": 0.0, "uri": "https://wikileaks.org/cable/2008/10/08JAKARTA1937.html", "authority": 0.0, "label": "08JAKARTA1937", "caption": "", "betweenness": 0.000134453, "pagerank": 8.58955e-06, "place": "JAKARTA", "multilevel": 7.0, "date": "2008-10-20", "colorindex": 0, "subjects": "HUMAN RIGHTS -- ENCOURAGING INDONESIA TO IMPLEMENT TRUTH COMMISSION REPORT", "nodeclass": "CONFIDENTIAL"}, {"degree": 2.0, "classification": "CONFIDENTIAL", "constraint": 0.902778, "color": "hsl(185,30%,54%)", "timestamp": 1227530000.0, "id": "n193209", "missing": 0.0, "uri": "https://wikileaks.org/cable/2008/11/08JAKARTA2158.html", "authority": 0.0, "label": "08JAKARTA2158", "caption": "", "betweenness": 0.0, "pagerank": 3.21382e-06, "place": "JAKARTA", "multilevel": 7.0, "date": "2008-11-24", "colorindex": 0, "subjects": "INDONESIA:  KEEPING MOMENTUM GOING AFTER THE CTF", "nodeclass": "CONFIDENTIAL"}, {"degree": 4.0, "classification": "CONFIDENTIAL", "constraint": 0.404983, "color": "hsl(185,30%,54%)", "timestamp": 1207210000.0, "id": "n193502", "missing": 0.0, "uri": "https://wikileaks.org/cable/2008/04/08JAKARTA672.html", "authority": 0.0, "label": "08JAKARTA672", "caption": "", "betweenness": 0.000246309, "pagerank": 5.05873e-06, "place": "JAKARTA", "multilevel": 7.0, "date": "2008-04-03", "colorindex": 0, "subjects": "EAST TIMOR/INDONESIA COMMISSION COMPLETES REPORT ON 1999 EVENTS", "nodeclass": "CONFIDENTIAL"}, {"degree": 4.0, "classification": "CONFIDENTIAL", "constraint": 0.363281, "color": "hsl(185,30%,54%)", "timestamp": 1207640000.0, "id": "n193516", "missing": 0.0, "uri": "https://wikileaks.org/cable/2008/04/08JAKARTA702.html", "authority": 0.0, "label": "08JAKARTA702", "caption": "", "betweenness": 0.000257347, "pagerank": 5.31854e-06, "place": "JAKARTA", "multilevel": 7.0, "date": "2008-04-08", "colorindex": 0, "subjects": "EAST TIMOR EX-MILITIA LEADER ACQUITTED", "nodeclass": "CONFIDENTIAL"}, {"degree": 2.0, "classification": "CONFIDENTIAL", "constraint": 0.78125, "color": "hsl(185,30%,54%)", "timestamp": 1208160000.0, "id": "n193540", "missing": 0.0, "uri": "https://wikileaks.org/cable/2008/04/08JAKARTA745.html", "authority": 0.0, "label": "08JAKARTA745", "caption": "", "betweenness": 0.0, "pagerank": 2.83626e-06, "place": "JAKARTA", "multilevel": 7.0, "date": "2008-04-14", "colorindex": 0, "subjects": "AMBASSADOR'S OP-ED PIECE HIGHLIGHTS DEMOCRACY, HUMAN RIGHTS", "nodeclass": "CONFIDENTIAL"}, {"degree": 6.0, "classification": "SECRET", "constraint": 0.335132, "color": "hsl(185,30%,54%)", "timestamp": 1209030000.0, "id": "n193579", "missing": 0.0, "uri": "https://wikileaks.org/cable/2008/04/08JAKARTA825.html", "authority": 0.0, "label": "08JAKARTA825", "caption": "", "betweenness": 0.000149, "pagerank": 7.36939e-06, "place": "JAKARTA", "multilevel": 7.0, "date": "2008-04-24", "colorindex": 0, "subjects": "EAST TIMOR/INDONESIA FINAL REPORT HOLDS GOI INSTITUTIONS ACCOUNTABLE", "nodeclass": "SECRET"}, {"degree": 2.0, "classification": "CONFIDENTIAL", "constraint": 0.666808, "color": "hsl(185,30%,54%)", "timestamp": 1211190000.0, "id": "n193667", "missing": 0.0, "uri": "https://wikileaks.org/cable/2008/05/08JAKARTA992.html", "authority": 0.0, "label": "08JAKARTA992", "caption": "", "betweenness": 0.0, "pagerank": 2.72313e-06, "place": "JAKARTA", "multilevel": 7.0, "date": "2008-05-19", "colorindex": 0, "subjects": "EAST TIMOR -- HUMAN RIGHTS ACTIVISTS SUPPORTIVE OF COMMISSION REPORT", "nodeclass": "CONFIDENTIAL"}], "links": [{"duration": 2009580.0, "source": 1, "betweenness": 4.33333, "target": 0}, {"duration": 7627620.0, "source": 9, "betweenness": 19.3333, "target": 0}, {"duration": 1363800.0, "source": 2, "betweenness": 14.6667, "target": 1}, {"duration": 4254240.0, "source": 9, "betweenness": 7.83333, "target": 2}, {"duration": 12026600.0, "source": 17, "betweenness": 21.8333, "target": 2}, {"duration": 76920.0, "source": 5, "betweenness": 16.0, "target": 3}, {"duration": 777660.0, "source": 7, "betweenness": 12.0, "target": 3}, {"duration": 426900.0, "source": 5, "betweenness": 26.0, "target": 4}, {"duration": 14422600.0, "source": 4, "betweenness": 16.5, "target": 9}, {"duration": 6650220.0, "source": 4, "betweenness": 21.5, "target": 17}, {"duration": 426900.0, "source": 5, "betweenness": 0.0, "target": 5}, {"duration": 435600.0, "source": 7, "betweenness": 22.0, "target": 6}, {"duration": 3026100.0, "source": 8, "betweenness": 18.0, "target": 6}, {"duration": 8111520.0, "source": 12, "betweenness": 44.0, "target": 6}, {"duration": 5956080.0, "source": 14, "betweenness": 15.5, "target": 9}, {"duration": 7772400.0, "source": 17, "betweenness": 15.0, "target": 9}, {"duration": 9931320.0, "source": 18, "betweenness": 6.16667, "target": 9}, {"duration": 0.0, "source": 12, "betweenness": 18.0, "target": 10}, {"duration": 333780.0, "source": 12, "betweenness": 17.0, "target": 11}, {"duration": 3377820.0, "source": 13, "betweenness": 1.0, "target": 11}, {"duration": 3044040.0, "source": 13, "betweenness": 17.0, "target": 12}, {"duration": 15453800.0, "source": 12, "betweenness": 72.0, "target": 17}, {"duration": 426900.0, "source": 15, "betweenness": 17.0, "target": 14}, {"duration": 952320.0, "source": 16, "betweenness": 17.0, "target": 14}, {"duration": 1816320.0, "source": 17, "betweenness": 32.5, "target": 14}, {"duration": 525420.0, "source": 16, "betweenness": 1.0, "target": 15}, {"duration": 2158920.0, "source": 18, "betweenness": 11.8333, "target": 17}]}