{"nodes": [{"degree": 2.0, "classification": "UNCLASSIFIED//FOR OFFICIAL USE ONLY", "missing": 0.0, "color": "hsl(180,52%,38%)", "timestamp": 1235760000.0, "id": "n241886", "constraint": 0.953125, "uri": "https://wikileaks.org/cable/2009/02/09BRIDGETOWN136.html", "authority": 0.0, "label": "09BRIDGETOWN136", "caption": "", "betweenness": 0.0, "pagerank": 4.09952e-06, "place": "BRIDGETOWN", "date": "2009-02-27", "colorindex": 0, "subjects": "THE STANFORD SAGA: IMPLICATIONS FOR THE EASTERN CARIBBEAN", "nodeclass": "UNCLASSIFIED-FOR-OFFICIAL-USE-ONLY"}, {"degree": 1.0, "classification": "CONFIDENTIAL", "missing": 0.0, "color": "hsl(180,52%,38%)", "timestamp": 1236200000.0, "id": "n241890", "constraint": 1.0, "uri": "https://wikileaks.org/cable/2009/03/09BRIDGETOWN144.html", "authority": 0.0, "label": "09BRIDGETOWN144", "caption": "", "betweenness": 0.0, "pagerank": 2.35722e-06, "place": "BRIDGETOWN", "date": "2009-03-04", "colorindex": 0, "subjects": "COLLAPSE OF TRINIDAD,S CL FINANCIAL GROUP RIPPLES ACROSS THE POND TO BARBADOS", "nodeclass": "CONFIDENTIAL"}, {"degree": 1.0, "classification": "UNCLASSIFIED", "missing": 0.0, "color": "hsl(180,52%,38%)", "timestamp": 1236270000.0, "id": "n241892", "constraint": 1.0, "uri": "https://wikileaks.org/cable/2009/03/09BRIDGETOWN146.html", "authority": 0.0, "label": "09BRIDGETOWN146", "caption": "", "betweenness": 0.0, "pagerank": 2.35722e-06, "place": "BRIDGETOWN", "date": "2009-03-05", "colorindex": 0, "subjects": "DOMINICA'S LABOR UNIONS STRUGGLING AMID ECONOMIC DOWNTURN", "nodeclass": "UNCLASSIFIED"}, {"degree": 2.0, "classification": "UNCLASSIFIED//FOR OFFICIAL USE ONLY", "missing": 0.0, "color": "hsl(180,52%,38%)", "timestamp": 1236800000.0, "id": "n241896", "constraint": 0.953125, "uri": "https://wikileaks.org/cable/2009/03/09BRIDGETOWN162.html", "authority": 0.0, "label": "09BRIDGETOWN162", "caption": "", "betweenness": 0.0, "pagerank": 4.09952e-06, "place": "BRIDGETOWN", "date": "2009-03-11", "colorindex": 0, "subjects": "EASTERN CARIBBEAN: TOURISM ECONOMY WAITING FOR THE BOTTOM TO FALL OUT", "nodeclass": "UNCLASSIFIED-FOR-OFFICIAL-USE-ONLY"}, {"degree": 4.0, "classification": "UNCLASSIFIED//FOR OFFICIAL USE ONLY", "missing": 0.0, "color": "hsl(180,52%,38%)", "timestamp": 1239050000.0, "id": "n241909", "constraint": 0.40625, "uri": "https://wikileaks.org/cable/2009/04/09BRIDGETOWN216.html", "authority": 0.0, "label": "09BRIDGETOWN216", "caption": "", "betweenness": 5.0, "pagerank": 8.12296e-06, "place": "BRIDGETOWN", "date": "2009-04-06", "colorindex": 0, "subjects": "CARIBBEAN WORKERS: DOWN, BUT NOT OUT", "nodeclass": "UNCLASSIFIED-FOR-OFFICIAL-USE-ONLY"}], "links": [{"duration": 1048860.0, "source": 3, "betweenness": 1.0, "target": 0}, {"duration": 3289860.0, "source": 4, "betweenness": 3.0, "target": 0}, {"duration": 2848380.0, "source": 4, "betweenness": 4.0, "target": 1}, {"duration": 2778720.0, "source": 4, "betweenness": 4.0, "target": 2}, {"duration": 2241000.0, "source": 4, "betweenness": 3.0, "target": 3}]}