{"nodes": [{"degree": 2.0, "classification": "UNCLASSIFIED//FOR OFFICIAL USE ONLY", "missing": 0.0, "color": "hsl(339,70%,31%)", "timestamp": 1178630000.0, "id": "n139486", "constraint": 0.5, "uri": "https://wikileaks.org/cable/2007/05/07KHARTOUM711.html", "authority": 0.0, "label": "07KHARTOUM711", "caption": "", "betweenness": 2.0, "pagerank": 5.46209e-06, "place": "KHARTOUM", "date": "2007-05-08", "colorindex": 1, "subjects": "SUDAN - NUBIAN VIEWS ON NILE DAM PROJECTS", "nodeclass": "UNCLASSIFIED-FOR-OFFICIAL-USE-ONLY"}, {"degree": 1.0, "classification": "", "missing": 1.0, "color": "hsl(339,70%,31%)", "timestamp": 1182290000.0, "id": "n139578", "constraint": 1.0, "uri": "", "authority": 0.0, "label": "07KHARTOUM968", "caption": "", "betweenness": 0.0, "pagerank": 2.95248e-06, "place": "KHARTOUM", "date": "2007-06-19", "colorindex": 1, "subjects": "", "nodeclass": "MISSING"}, {"degree": 2.0, "classification": "CONFIDENTIAL", "missing": 0.0, "color": "hsl(339,70%,31%)", "timestamp": 1182440000.0, "id": "n139587", "constraint": 0.5, "uri": "https://wikileaks.org/cable/2007/06/07KHARTOUM983.html", "authority": 0.0, "label": "07KHARTOUM983", "caption": "", "betweenness": 2.0, "pagerank": 5.46209e-06, "place": "KHARTOUM", "date": "2007-06-21", "colorindex": 1, "subjects": "KAJBAR VIDEO SYMBOLIZES SUFFERING OF DARFUR AND THE SUDANESE PEOPLE AS A WHOLE", "nodeclass": "CONFIDENTIAL"}, {"degree": 1.0, "classification": "", "missing": 1.0, "color": "hsl(99,67%,26%)", "timestamp": 0.0, "id": "n157393", "constraint": 1.0, "uri": "", "authority": 0.0, "label": "07SECSTATE56709", "caption": "", "betweenness": 0.0, "pagerank": 2.95248e-06, "place": "SECSTATE", "date": null, "colorindex": 0, "subjects": "", "nodeclass": "MISSING"}], "links": [{"duration": 3809280.0, "source": 2, "betweenness": 4.0, "target": 0}, {"duration": 0.0, "source": 0, "betweenness": 3.0, "target": 3}, {"duration": 0.0, "source": 2, "betweenness": 3.0, "target": 1}]}