{"nodes": [{"degree": 1.0, "classification": "", "constraint": 1.0, "color": "hsl(229,88%,55%)", "timestamp": 0.0, "id": "n450", "missing": 1.0, "uri": "", "authority": 1.06724e-14, "label": "00KUWAIT3466", "caption": "", "betweenness": 0.0, "pagerank": 1.63743e-06, "place": "KUWAIT", "multilevel": 9.0, "date": null, "colorindex": 2, "subjects": "", "nodeclass": "MISSING"}, {"degree": 1.0, "classification": "UNCLASSIFIED", "constraint": 1.0, "color": "hsl(229,88%,55%)", "timestamp": 1165830000.0, "id": "n88845", "missing": 0.0, "uri": "https://wikileaks.org/cable/2006/12/06KUWAIT4617.html", "authority": 5.20978e-15, "label": "06KUWAIT4617", "caption": "", "betweenness": 0.0, "pagerank": 1.41434e-06, "place": "KUWAIT", "multilevel": 9.0, "date": "2006-12-11", "colorindex": 2, "subjects": "KUWAIT MEDIA REACTION - TERROR FUNDING, IRAN, IRAQ, AND NATO", "nodeclass": "UNCLASSIFIED"}, {"degree": 13.0, "classification": "CONFIDENTIAL//NOFORN", "constraint": 0.128382, "color": "hsl(229,88%,55%)", "timestamp": 1165930000.0, "id": "n88862", "missing": 0.0, "uri": "https://wikileaks.org/cable/2006/12/06KUWAIT4637.html", "authority": 1.57423e-13, "label": "06KUWAIT4637", "caption": "(NOTAL)", "betweenness": 0.0062339, "pagerank": 1.1979e-05, "place": "KUWAIT", "multilevel": 9.0, "date": "2006-12-12", "colorindex": 2, "subjects": "TERROR FINANCE:  KUWAITI REACTION TO U.S. DESIGNATION OF TERRORIST FACILITATORS", "nodeclass": "CONFIDENTIAL-NOFORN"}, {"degree": 2.0, "classification": "CONFIDENTIAL", "constraint": 0.5, "color": "hsl(178,68%,51%)", "timestamp": 1198070000.0, "id": "n123062", "missing": 0.0, "uri": "https://wikileaks.org/cable/2007/12/07BAGHDAD4136.html", "authority": 3.53673e-08, "label": "07BAGHDAD4136", "caption": "", "betweenness": 0.000908881, "pagerank": 2.92097e-06, "place": "BAGHDAD", "multilevel": 9.0, "date": "2007-12-19", "colorindex": 4, "subjects": "KUWAITI NAVY IN DISPUTE WITH COALITION-CONTRACTED VESSELS", "nodeclass": "CONFIDENTIAL"}, {"degree": 1.0, "classification": "SECRET", "constraint": 1.0, "color": "hsl(229,88%,55%)", "timestamp": 1195630000.0, "id": "n140991", "missing": 0.0, "uri": "https://wikileaks.org/cable/2007/11/07KUWAIT1651.html", "authority": 1.70908e-15, "label": "07KUWAIT1651", "caption": "", "betweenness": 0.0, "pagerank": 1.83466e-06, "place": "KUWAIT", "multilevel": 9.0, "date": "2007-11-21", "colorindex": 2, "subjects": "DEMARCHE DELIVERED:  USG CONCERNS REGARDING GOK FAILURE TO IMPLEMENT GTMO SECURITY ASSURANCES", "nodeclass": "SECRET"}, {"degree": 1.0, "classification": "", "constraint": 1.0, "color": "hsl(99,92%,51%)", "timestamp": 0.0, "id": "n156950", "missing": 1.0, "uri": "", "authority": 2.31857e-16, "label": "07SECSTATE165957", "caption": "", "betweenness": 0.0, "pagerank": 1.93008e-06, "place": "SECSTATE", "multilevel": 9.0, "date": null, "colorindex": 9, "subjects": "", "nodeclass": "MISSING"}, {"degree": 2.0, "classification": "UNCLASSIFIED", "constraint": 0.846944, "color": "hsl(211,99%,67%)", "timestamp": 1203930000.0, "id": "n172305", "missing": 0.0, "uri": "https://wikileaks.org/cable/2008/02/08AITTAIPEI261.html", "authority": 1.20484e-13, "label": "08AITTAIPEI261", "caption": "", "betweenness": 0.0, "pagerank": 2.67579e-06, "place": "AITTAIPEI", "multilevel": 9.0, "date": "2008-02-25", "colorindex": 0, "subjects": "TERRORISM FINANCE: DESIGNATION OF THREE KUWAIT-BASED TERRORIST FACILITATORS", "nodeclass": "UNCLASSIFIED"}, {"degree": 2.0, "classification": "UNCLASSIFIED", "constraint": 0.846944, "color": "hsl(211,99%,67%)", "timestamp": 1204710000.0, "id": "n172313", "missing": 0.0, "uri": "https://wikileaks.org/cable/2008/03/08AITTAIPEI301.html", "authority": 1.20484e-13, "label": "08AITTAIPEI301", "caption": "", "betweenness": 0.0, "pagerank": 2.67579e-06, "place": "AITTAIPEI", "multilevel": 9.0, "date": "2008-03-05", "colorindex": 0, "subjects": "TERRORISM FINANCE: DESIGNATION OF THREE KUWAIT-BASED TERRORIST FACILITATORS", "nodeclass": "UNCLASSIFIED"}, {"degree": 2.0, "classification": "", "constraint": 0.5, "color": "hsl(178,68%,51%)", "timestamp": 0.0, "id": "n177871", "missing": 1.0, "uri": "", "authority": 1.29313e-12, "label": "08BAGHDAD4136", "caption": "", "betweenness": 8.46202e-07, "pagerank": 2.78775e-06, "place": "BAGHDAD", "multilevel": 9.0, "date": null, "colorindex": 4, "subjects": "", "nodeclass": "MISSING"}, {"degree": 3.0, "classification": "CONFIDENTIAL", "constraint": 0.333333, "color": "hsl(178,68%,51%)", "timestamp": 1199720000.0, "id": "n177919", "missing": 0.0, "uri": "https://wikileaks.org/cable/2008/01/08BAGHDAD50.html", "authority": 1.17286e-09, "label": "08BAGHDAD50", "caption": "", "betweenness": 0.00146615, "pagerank": 4.07753e-06, "place": "BAGHDAD", "multilevel": 9.0, "date": "2008-01-07", "colorindex": 4, "subjects": "SEEKING KUWAITI CONCURRENCE ON MNF-I SALVAGE OPERATIONS", "nodeclass": "CONFIDENTIAL"}, {"degree": 1.0, "classification": "UNCLASSIFIED", "constraint": 1.0, "color": "hsl(293,96%,79%)", "timestamp": 1201870000.0, "id": "n195092", "missing": 0.0, "uri": "https://wikileaks.org/cable/2008/02/08KATHMANDU143.html", "authority": 1.16498e-13, "label": "08KATHMANDU143", "caption": "", "betweenness": 0.0, "pagerank": 1.53858e-06, "place": "KATHMANDU", "multilevel": 9.0, "date": "2008-02-01", "colorindex": 8, "subjects": "TERRORISM FINANCE: DESIGNATION OF THREE KUWAIT-BASED TERRORIST FACILITATORS DELIVERED", "nodeclass": "UNCLASSIFIED"}, {"degree": 2.0, "classification": "CONFIDENTIAL", "constraint": 0.5, "color": "hsl(229,88%,55%)", "timestamp": 1201660000.0, "id": "n197635", "missing": 0.0, "uri": "https://wikileaks.org/cable/2008/01/08KUWAIT113.html", "authority": 7.02227e-15, "label": "08KUWAIT113", "caption": "", "betweenness": 1.99914e-05, "pagerank": 3.05644e-06, "place": "KUWAIT", "multilevel": 9.0, "date": "2008-01-30", "colorindex": 2, "subjects": "DEMARCHE DELIVERED: GTMO ADMINISTRATIVE REVIEW BOARD DETERMINATIONS", "nodeclass": "CONFIDENTIAL"}, {"degree": 3.0, "classification": "CONFIDENTIAL", "constraint": 0.437505, "color": "hsl(229,88%,55%)", "timestamp": 1199370000.0, "id": "n197672", "missing": 0.0, "uri": "https://wikileaks.org/cable/2008/01/08KUWAIT12.html", "authority": 5.16607e-14, "label": "08KUWAIT12", "caption": "", "betweenness": 1.99914e-05, "pagerank": 4.24787e-06, "place": "KUWAIT", "multilevel": 9.0, "date": "2008-01-03", "colorindex": 2, "subjects": "GOK LOOKING FORWARD TO POTUS VISIT; AMIR TO RAISE GTMO ISSUE", "nodeclass": "CONFIDENTIAL"}, {"degree": 7.0, "classification": "CONFIDENTIAL", "constraint": 0.188422, "color": "hsl(229,88%,55%)", "timestamp": 1201790000.0, "id": "n197689", "missing": 0.0, "uri": "https://wikileaks.org/cable/2008/01/08KUWAIT128.html", "authority": 2.07395e-12, "label": "08KUWAIT128", "caption": "", "betweenness": 0.00332138, "pagerank": 6.28921e-06, "place": "KUWAIT", "multilevel": 9.0, "date": "2008-01-31", "colorindex": 2, "subjects": "TERROR FINANCE: DESIGNEES CONTINUE TO RANT, WITH SOME SUPPORT FROM PARLIAMENT", "nodeclass": "CONFIDENTIAL"}, {"degree": 3.0, "classification": "CONFIDENTIAL", "constraint": 0.333333, "color": "hsl(229,88%,55%)", "timestamp": 1199440000.0, "id": "n197694", "missing": 0.0, "uri": "https://wikileaks.org/cable/2008/01/08KUWAIT14.html", "authority": 1.35472e-13, "label": "08KUWAIT14", "caption": "", "betweenness": 1.44493e-05, "pagerank": 3.85444e-06, "place": "KUWAIT", "multilevel": 9.0, "date": "2008-01-04", "colorindex": 2, "subjects": "KUWAIT MFA U/S: SYRIA AND IRAN", "nodeclass": "CONFIDENTIAL"}, {"degree": 4.0, "classification": "CONFIDENTIAL", "constraint": 0.25, "color": "hsl(229,88%,55%)", "timestamp": 1199440000.0, "id": "n197696", "missing": 0.0, "uri": "https://wikileaks.org/cable/2008/01/08KUWAIT15.html", "authority": 3.89446e-11, "label": "08KUWAIT15", "caption": "", "betweenness": 0.000893351, "pagerank": 5.00974e-06, "place": "KUWAIT", "multilevel": 9.0, "date": "2008-01-04", "colorindex": 2, "subjects": "KUWAIT MFA U/S ON KUWAITI MILITARY INCIDENT, IRAQI BORDER ISSUES", "nodeclass": "CONFIDENTIAL"}, {"degree": 3.0, "classification": "CONFIDENTIAL", "constraint": 0.435997, "color": "hsl(229,88%,55%)", "timestamp": 1202400000.0, "id": "n197700", "missing": 0.0, "uri": "https://wikileaks.org/cable/2008/02/08KUWAIT154.html", "authority": 4.99746e-13, "label": "08KUWAIT154", "caption": "", "betweenness": 0.000151164, "pagerank": 3.48063e-06, "place": "KUWAIT", "multilevel": 9.0, "date": "2008-02-07", "colorindex": 2, "subjects": "REPORTED DEATH THREAT AGAINST MP OPPOSING GENDER SEGREGATION IN SCHOOLS", "nodeclass": "CONFIDENTIAL"}, {"degree": 1.0, "classification": "", "constraint": 1.0, "color": "hsl(229,88%,55%)", "timestamp": 0.0, "id": "n197702", "missing": 1.0, "uri": "", "authority": 1.94252e-13, "label": "08KUWAIT1562", "caption": "", "betweenness": 0.0, "pagerank": 1.71126e-06, "place": "KUWAIT", "multilevel": 9.0, "date": null, "colorindex": 2, "subjects": "", "nodeclass": "MISSING"}, {"degree": 1.0, "classification": "", "constraint": 1.0, "color": "hsl(229,88%,55%)", "timestamp": 0.0, "id": "n197705", "missing": 1.0, "uri": "", "authority": 1.94252e-13, "label": "08KUWAIT1590", "caption": "", "betweenness": 0.0, "pagerank": 1.71126e-06, "place": "KUWAIT", "multilevel": 9.0, "date": null, "colorindex": 2, "subjects": "", "nodeclass": "MISSING"}, {"degree": 1.0, "classification": "", "constraint": 1.0, "color": "hsl(229,88%,55%)", "timestamp": 0.0, "id": "n197707", "missing": 1.0, "uri": "", "authority": 1.70908e-15, "label": "08KUWAIT1651", "caption": "", "betweenness": 0.0, "pagerank": 1.83466e-06, "place": "KUWAIT", "multilevel": 9.0, "date": null, "colorindex": 2, "subjects": "", "nodeclass": "MISSING"}, {"degree": 2.0, "classification": "", "constraint": 0.5, "color": "hsl(229,88%,55%)", "timestamp": 0.0, "id": "n197708", "missing": 1.0, "uri": "", "authority": 1.29313e-12, "label": "08KUWAIT1655", "caption": "", "betweenness": 8.46202e-07, "pagerank": 2.78775e-06, "place": "KUWAIT", "multilevel": 9.0, "date": null, "colorindex": 2, "subjects": "", "nodeclass": "MISSING"}, {"degree": 1.0, "classification": "", "constraint": 1.0, "color": "hsl(229,88%,55%)", "timestamp": 0.0, "id": "n197715", "missing": 1.0, "uri": "", "authority": 1.94252e-13, "label": "08KUWAIT1760", "caption": "", "betweenness": 0.0, "pagerank": 1.71126e-06, "place": "KUWAIT", "multilevel": 9.0, "date": null, "colorindex": 2, "subjects": "", "nodeclass": "MISSING"}, {"degree": 1.0, "classification": "", "constraint": 1.0, "color": "hsl(229,88%,55%)", "timestamp": 0.0, "id": "n197716", "missing": 1.0, "uri": "", "authority": 1.94252e-13, "label": "08KUWAIT1762", "caption": "", "betweenness": 0.0, "pagerank": 1.71126e-06, "place": "KUWAIT", "multilevel": 9.0, "date": null, "colorindex": 2, "subjects": "", "nodeclass": "MISSING"}, {"degree": 10.0, "classification": "CONFIDENTIAL", "constraint": 0.186843, "color": "hsl(229,88%,55%)", "timestamp": 1203860000.0, "id": "n197735", "missing": 0.0, "uri": "https://wikileaks.org/cable/2008/02/08KUWAIT218.html", "authority": 5.80119e-13, "label": "08KUWAIT218", "caption": "", "betweenness": 0.00270027, "pagerank": 8.8302e-06, "place": "KUWAIT", "multilevel": 9.0, "date": "2008-02-24", "colorindex": 2, "subjects": "TERROR FINANCE: MFA ON GOK OBLIGATIONS/HUMANITARIAN CONCERNS REGARDING FAMILIES OF UNSCR 1267 DESIGNEES", "nodeclass": "CONFIDENTIAL"}, {"degree": 8.0, "classification": "CONFIDENTIAL", "constraint": 0.251855, "color": "hsl(229,88%,55%)", "timestamp": 1204190000.0, "id": "n197738", "missing": 0.0, "uri": "https://wikileaks.org/cable/2008/02/08KUWAIT227.html", "authority": 5.24396e-13, "label": "08KUWAIT227", "caption": "", "betweenness": 0.000897095, "pagerank": 6.87134e-06, "place": "KUWAIT", "multilevel": 9.0, "date": "2008-02-28", "colorindex": 2, "subjects": "TERROR FINANCE: MFA ON GOK OBLIGATIONS/HUMANITARIAN CONCERNS REGARDING FAMILIES OF UNSCR 1267 DESIGNEES", "nodeclass": "CONFIDENTIAL"}, {"degree": 9.0, "classification": "SECRET//NOFORN", "constraint": 0.116863, "color": "hsl(229,88%,55%)", "timestamp": 1204770000.0, "id": "n197746", "missing": 0.0, "uri": "https://wikileaks.org/cable/2008/03/08KUWAIT246.html", "authority": 4.79211e-11, "label": "08KUWAIT246", "caption": "", "betweenness": 0.00896911, "pagerank": 9.10014e-06, "place": "KUWAIT", "multilevel": 9.0, "date": "2008-03-06", "colorindex": 2, "subjects": "KUWAIT SCENESETTER FOR MARCH 10 GULF SECURITY DIALOGUE", "nodeclass": "SECRET-NOFORN"}, {"degree": 6.0, "classification": "SECRET", "constraint": 0.176327, "color": "hsl(229,88%,55%)", "timestamp": 1205320000.0, "id": "n197756", "missing": 0.0, "uri": "https://wikileaks.org/cable/2008/03/08KUWAIT283.html", "authority": 1.55561e-12, "label": "08KUWAIT283", "caption": "", "betweenness": 0.000433591, "pagerank": 6.5143e-06, "place": "KUWAIT", "multilevel": 9.0, "date": "2008-03-12", "colorindex": 2, "subjects": "(C) TERROR FINANCE:  GOK SLOW TO FREEZE ASSETS OF THREE KUWAITI UNSCR 1267 DESIGNEES", "nodeclass": "SECRET"}, {"degree": 1.0, "classification": "CONFIDENTIAL", "constraint": 1.0, "color": "hsl(229,88%,55%)", "timestamp": 1199800000.0, "id": "n197777", "missing": 0.0, "uri": "https://wikileaks.org/cable/2008/01/08KUWAIT35.html", "authority": 1.94252e-13, "label": "08KUWAIT35", "caption": "", "betweenness": 0.0, "pagerank": 1.71126e-06, "place": "KUWAIT", "multilevel": 9.0, "date": "2008-01-08", "colorindex": 2, "subjects": "PROMINENT WOMEN'S ACTIVIST ON DISSOLUTION RUMORS AND THE FUTURE OF KUWAIT", "nodeclass": "CONFIDENTIAL"}, {"degree": 10.0, "classification": "CONFIDENTIAL", "constraint": 0.109375, "color": "hsl(229,88%,55%)", "timestamp": 1199970000.0, "id": "n197799", "missing": 0.0, "uri": "https://wikileaks.org/cable/2008/01/08KUWAIT43.html", "authority": 5.87052e-12, "label": "08KUWAIT43", "caption": "", "betweenness": 0.00156102, "pagerank": 1.27078e-05, "place": "KUWAIT", "multilevel": 9.0, "date": "2008-01-10", "colorindex": 2, "subjects": "PARLIAMENT'S GRILLING MORE FIZZLE THAN SIZZLE", "nodeclass": "CONFIDENTIAL"}, {"degree": 10.0, "classification": "CONFIDENTIAL", "constraint": 0.238054, "color": "hsl(229,88%,55%)", "timestamp": 1209660000.0, "id": "n197811", "missing": 0.0, "uri": "https://wikileaks.org/cable/2008/05/08KUWAIT476.html", "authority": 5.45783e-13, "label": "08KUWAIT476", "caption": "", "betweenness": 0.000904338, "pagerank": 8.47993e-06, "place": "KUWAIT", "multilevel": 9.0, "date": "2008-05-01", "colorindex": 2, "subjects": "TERROR FINANCE:   DESPITE GOK CONFIRMATION UN 1267 DESIGNEE ASSETS REMAIN UNFROZEN", "nodeclass": "CONFIDENTIAL"}, {"degree": 3.0, "classification": "SECRET", "constraint": 0.437505, "color": "hsl(229,88%,55%)", "timestamp": 1200000000.0, "id": "n197813", "missing": 0.0, "uri": "https://wikileaks.org/cable/2008/01/08KUWAIT48.html", "authority": 5.16607e-14, "label": "08KUWAIT48", "caption": "", "betweenness": 1.99914e-05, "pagerank": 4.24787e-06, "place": "KUWAIT", "multilevel": 9.0, "date": "2008-01-10", "colorindex": 2, "subjects": "GOK PROVIDES NEW ASSURANCE ON GTMO ON EVE OF POTUS VISIT", "nodeclass": "SECRET"}, {"degree": 10.0, "classification": "CONFIDENTIAL", "constraint": 0.238054, "color": "hsl(229,88%,55%)", "timestamp": 1211110000.0, "id": "n197842", "missing": 0.0, "uri": "https://wikileaks.org/cable/2008/05/08KUWAIT560.html", "authority": 5.45783e-13, "label": "08KUWAIT560", "caption": "", "betweenness": 0.000904338, "pagerank": 8.47993e-06, "place": "KUWAIT", "multilevel": 9.0, "date": "2008-05-18", "colorindex": 2, "subjects": "TERROR FINANCE:  KUWAIT FINALLY FREEZES ASSETS OF THREE FINANCIERS", "nodeclass": "CONFIDENTIAL"}, {"degree": 1.0, "classification": "UNCLASSIFIED", "constraint": 1.0, "color": "hsl(229,88%,55%)", "timestamp": 1215510000.0, "id": "n197914", "missing": 0.0, "uri": "https://wikileaks.org/cable/2008/07/08KUWAIT769.html", "authority": 1.01193e-14, "label": "08KUWAIT769", "caption": "", "betweenness": 0.0, "pagerank": 1.72719e-06, "place": "KUWAIT", "multilevel": 9.0, "date": "2008-07-08", "colorindex": 2, "subjects": "AMBASSADOR DISCUSSES GENDER SEGREGATION WITH U/S FOR HIGHER EDUCATION", "nodeclass": "UNCLASSIFIED"}, {"degree": 9.0, "classification": "SECRET//NOFORN", "constraint": 0.209318, "color": "hsl(229,88%,55%)", "timestamp": 1200590000.0, "id": "n197925", "missing": 0.0, "uri": "https://wikileaks.org/cable/2008/01/08KUWAIT79.html", "authority": 2.11999e-13, "label": "08KUWAIT79", "caption": "", "betweenness": 5.891e-05, "pagerank": 8.30939e-06, "place": "KUWAIT", "multilevel": 9.0, "date": "2008-01-17", "colorindex": 2, "subjects": "GOK APPEALS TO STOP DESIGNATION OF KUWAITI TERRORIST FINANCIERS", "nodeclass": "SECRET-NOFORN"}, {"degree": 3.0, "classification": "CONFIDENTIAL", "constraint": 0.391208, "color": "hsl(229,88%,55%)", "timestamp": 1216210000.0, "id": "n197931", "missing": 0.0, "uri": "https://wikileaks.org/cable/2008/07/08KUWAIT804.html", "authority": 3.05828e-13, "label": "08KUWAIT804", "caption": "", "betweenness": 1.99914e-05, "pagerank": 3.86858e-06, "place": "KUWAIT", "multilevel": 9.0, "date": "2008-07-16", "colorindex": 2, "subjects": "EDUCATION MINISTER:  SLOW ROLLING GENDER SEGREGATION", "nodeclass": "CONFIDENTIAL"}, {"degree": 2.0, "classification": "CONFIDENTIAL", "constraint": 0.5, "color": "hsl(229,88%,55%)", "timestamp": 1200660000.0, "id": "n197934", "missing": 0.0, "uri": "https://wikileaks.org/cable/2008/01/08KUWAIT81.html", "authority": 4.99497e-14, "label": "08KUWAIT81", "caption": "", "betweenness": 1.99914e-05, "pagerank": 3.16442e-06, "place": "KUWAIT", "multilevel": 9.0, "date": "2008-01-18", "colorindex": 2, "subjects": "READOUT OF KUWAITI FOREIGN MINISTER'S JAN. 15-16 VISIT TO TEHRAN", "nodeclass": "CONFIDENTIAL"}, {"degree": 13.0, "classification": "CONFIDENTIAL", "constraint": 0.133311, "color": "hsl(229,88%,55%)", "timestamp": 1201100000.0, "id": "n197960", "missing": 0.0, "uri": "https://wikileaks.org/cable/2008/01/08KUWAIT90.html", "authority": 8.90985e-12, "label": "08KUWAIT90", "caption": "", "betweenness": 0.00299095, "pagerank": 1.167e-05, "place": "KUWAIT", "multilevel": 9.0, "date": "2008-01-23", "colorindex": 2, "subjects": "EDUCATION MINISTER SURVIVES VOTE OF NO CONFIDENCE/PAYOFF IS GENDER SEGREGATION", "nodeclass": "CONFIDENTIAL"}, {"degree": 8.0, "classification": "CONFIDENTIAL", "constraint": 0.286293, "color": "hsl(229,88%,55%)", "timestamp": 1201190000.0, "id": "n197982", "missing": 0.0, "uri": "https://wikileaks.org/cable/2008/01/08KUWAIT97.html", "authority": 4.48342e-13, "label": "08KUWAIT97", "caption": "", "betweenness": 0.000121469, "pagerank": 6.64808e-06, "place": "KUWAIT", "multilevel": 9.0, "date": "2008-01-24", "colorindex": 2, "subjects": "TERROR FINANCE:  LIMITED MEDIA REACTION SO FAR TO 1267 DESIGNATIONS", "nodeclass": "CONFIDENTIAL"}, {"degree": 13.0, "classification": "CONFIDENTIAL", "constraint": 0.117226, "color": "hsl(229,88%,55%)", "timestamp": 1201190000.0, "id": "n197986", "missing": 0.0, "uri": "https://wikileaks.org/cable/2008/01/08KUWAIT98.html", "authority": 1.50789e-12, "label": "08KUWAIT98", "caption": "", "betweenness": 0.00250266, "pagerank": 1.30574e-05, "place": "KUWAIT", "multilevel": 9.0, "date": "2008-01-24", "colorindex": 2, "subjects": "KUWAIT MFA U/S ON IRAQ, GTMO, 1267 DESIGNEES", "nodeclass": "CONFIDENTIAL"}, {"degree": 1.0, "classification": "UNCLASSIFIED", "constraint": 1.0, "color": "hsl(229,88%,55%)", "timestamp": 1201270000.0, "id": "n197988", "missing": 0.0, "uri": "https://wikileaks.org/cable/2008/01/08KUWAIT99.html", "authority": 1.65237e-15, "label": "08KUWAIT99", "caption": "", "betweenness": 0.0, "pagerank": 1.97597e-06, "place": "KUWAIT", "multilevel": 9.0, "date": "2008-01-25", "colorindex": 2, "subjects": "KUWAIT MEDIA REACTION - VISIT OF KUWAIT FM TO TEHRAN", "nodeclass": "UNCLASSIFIED"}, {"degree": 1.0, "classification": "UNCLASSIFIED//FOR OFFICIAL USE ONLY", "constraint": 1.0, "color": "hsl(71,70%,76%)", "timestamp": 1202390000.0, "id": "n202586", "missing": 0.0, "uri": "https://wikileaks.org/cable/2008/02/08MINSK83.html", "authority": 1.16498e-13, "label": "08MINSK83", "caption": "", "betweenness": 0.0, "pagerank": 1.53858e-06, "place": "MINSK", "multilevel": 9.0, "date": "2008-02-07", "colorindex": 5, "subjects": "TERRORISM FINANCE LIST 83 DELIVERED TO BELARUS", "nodeclass": "UNCLASSIFIED-FOR-OFFICIAL-USE-ONLY"}, {"degree": 1.0, "classification": "UNCLASSIFIED//FOR OFFICIAL USE ONLY", "constraint": 1.0, "color": "hsl(262,72%,69%)", "timestamp": 1202390000.0, "id": "n206483", "missing": 0.0, "uri": "https://wikileaks.org/cable/2008/02/08OSLO69.html", "authority": 1.16498e-13, "label": "08OSLO69", "caption": "", "betweenness": 0.0, "pagerank": 1.53858e-06, "place": "OSLO", "multilevel": 9.0, "date": "2008-02-07", "colorindex": 7, "subjects": "TERRORISM FINANCE: DESIGNATION OF THREE KUWAIT-BASED TERRORIST FACILITATORS", "nodeclass": "UNCLASSIFIED-FOR-OFFICIAL-USE-ONLY"}, {"degree": 3.0, "classification": "", "constraint": 0.38, "color": "hsl(224,92%,96%)", "timestamp": 0.0, "id": "n217142", "missing": 1.0, "uri": "", "authority": 8.75945e-14, "label": "08STATE192459", "caption": "", "betweenness": 2.36599e-07, "pagerank": 2.99554e-06, "place": "STATE", "multilevel": 9.0, "date": null, "colorindex": 3, "subjects": "", "nodeclass": "MISSING"}, {"degree": 15.0, "classification": "", "constraint": 0.0912401, "color": "hsl(224,92%,96%)", "timestamp": 1201170000.0, "id": "n219007", "missing": 1.0, "uri": "", "authority": 3.52069e-12, "label": "08STATE7443", "caption": "", "betweenness": 0.00560388, "pagerank": 1.60145e-05, "place": "STATE", "multilevel": 9.0, "date": "2008-01-24", "colorindex": 3, "subjects": "", "nodeclass": "MISSING"}, {"degree": 1.0, "classification": "UNCLASSIFIED", "constraint": 1.0, "color": "hsl(150,97%,67%)", "timestamp": 1202820000.0, "id": "n220851", "missing": 0.0, "uri": "https://wikileaks.org/cable/2008/02/08TASHKENT187.html", "authority": 1.16498e-13, "label": "08TASHKENT187", "caption": "", "betweenness": 0.0, "pagerank": 1.53858e-06, "place": "TASHKENT", "multilevel": 9.0, "date": "2008-02-12", "colorindex": 1, "subjects": "TERRORISM FINANCE: DESIGNATION OF THREE KUWAIT-BASED TERRORIST FACILITATORS - UZBEKISTAN", "nodeclass": "UNCLASSIFIED"}, {"degree": 1.0, "classification": "UNCLASSIFIED", "constraint": 1.0, "color": "hsl(312,79%,97%)", "timestamp": 1201710000.0, "id": "n224962", "missing": 0.0, "uri": "https://wikileaks.org/cable/2008/01/08TUNIS94.html", "authority": 1.16498e-13, "label": "08TUNIS94", "caption": "", "betweenness": 0.0, "pagerank": 1.53858e-06, "place": "TUNIS", "multilevel": 9.0, "date": "2008-01-30", "colorindex": 6, "subjects": "TERRORISM FINANCE: DESIGNATION OF THREE KUWAIT-BASED TERRORIST FACILITATORS", "nodeclass": "UNCLASSIFIED"}, {"degree": 6.0, "classification": "CONFIDENTIAL", "constraint": 0.224925, "color": "hsl(229,88%,55%)", "timestamp": 1256220000.0, "id": "n258530", "missing": 0.0, "uri": "https://wikileaks.org/cable/2009/10/09KUWAIT1013.html", "authority": 3.22539e-13, "label": "09KUWAIT1013", "caption": "", "betweenness": 0.00232756, "pagerank": 7.10352e-06, "place": "KUWAIT", "multilevel": 9.0, "date": "2009-10-22", "colorindex": 2, "subjects": "KUWAITI FEMALE MP FIGHTS FOR RETURN TO COEDUCATION", "nodeclass": "CONFIDENTIAL"}, {"degree": 1.0, "classification": "SECRET", "constraint": 1.0, "color": "hsl(229,88%,55%)", "timestamp": 1241440000.0, "id": "n258757", "missing": 0.0, "uri": "https://wikileaks.org/cable/2009/05/09KUWAIT445.html", "authority": 5.1474e-14, "label": "09KUWAIT445", "caption": "", "betweenness": 0.0, "pagerank": 1.55395e-06, "place": "KUWAIT", "multilevel": 9.0, "date": "2009-05-04", "colorindex": 2, "subjects": "KUWAITI NSB DEPUTY WARY OF AL-MALIKI AND IRAN", "nodeclass": "SECRET"}, {"degree": 1.0, "classification": "", "constraint": 1.0, "color": "hsl(229,88%,55%)", "timestamp": 0.0, "id": "n305476", "missing": 1.0, "uri": "", "authority": 1.06724e-14, "label": "94KUWAIT4046", "caption": "", "betweenness": 0.0, "pagerank": 1.63743e-06, "place": "KUWAIT", "multilevel": 9.0, "date": null, "colorindex": 2, "subjects": "", "nodeclass": "MISSING"}], "links": [{"duration": 0.0, "source": 46, "betweenness": 48.0, "target": 0}, {"duration": 100980.0, "source": 2, "betweenness": 48.0, "target": 1}, {"duration": 35859800.0, "source": 13, "betweenness": 18.5538, "target": 2}, {"duration": 37928900.0, "source": 23, "betweenness": 20.025, "target": 2}, {"duration": 38260500.0, "source": 24, "betweenness": 16.025, "target": 2}, {"duration": 43725800.0, "source": 29, "betweenness": 16.9769, "target": 2}, {"duration": 45177800.0, "source": 31, "betweenness": 16.9769, "target": 2}, {"duration": 35259400.0, "source": 37, "betweenness": 7.33333, "target": 2}, {"duration": 1649460.0, "source": 9, "betweenness": 48.0, "target": 3}, {"duration": 4363080.0, "source": 30, "betweenness": 48.0, "target": 4}, {"duration": 0.0, "source": 11, "betweenness": 48.0, "target": 5}, {"duration": 776820.0, "source": 7, "betweenness": 1.0, "target": 6}, {"duration": 0.0, "source": 6, "betweenness": 47.0, "target": 43}, {"duration": 0.0, "source": 7, "betweenness": 47.0, "target": 43}, {"duration": 0.0, "source": 14, "betweenness": 24.0, "target": 8}, {"duration": 0.0, "source": 15, "betweenness": 26.0, "target": 8}, {"duration": 281100.0, "source": 9, "betweenness": 94.0, "target": 15}, {"duration": 0.0, "source": 10, "betweenness": 48.0, "target": 43}, {"duration": 1073040.0, "source": 11, "betweenness": 94.0, "target": 33}, {"duration": 0.0, "source": 12, "betweenness": 48.0, "target": 19}, {"duration": 623820.0, "source": 30, "betweenness": 4.0, "target": 12}, {"duration": 1819140.0, "source": 38, "betweenness": 90.0, "target": 12}, {"duration": 2984040.0, "source": 25, "betweenness": 28.5, "target": 13}, {"duration": 1199940.0, "source": 13, "betweenness": 19.1205, "target": 33}, {"duration": 688740.0, "source": 13, "betweenness": 79.2538, "target": 36}, {"duration": 600420.0, "source": 13, "betweenness": 6.08718, "target": 37}, {"duration": 599160.0, "source": 13, "betweenness": 88.7872, "target": 38}, {"duration": 0.0, "source": 13, "betweenness": 71.0974, "target": 43}, {"duration": 0.0, "source": 14, "betweenness": 24.0, "target": 20}, {"duration": 1752120.0, "source": 38, "betweenness": 87.0, "target": 14}, {"duration": 0.0, "source": 15, "betweenness": 26.0, "target": 20}, {"duration": 1752120.0, "source": 38, "betweenness": 173.0, "target": 15}, {"duration": 2432940.0, "source": 16, "betweenness": 15.0, "target": 28}, {"duration": 1298340.0, "source": 16, "betweenness": 38.0, "target": 36}, {"duration": 53816800.0, "source": 46, "betweenness": 13.0, "target": 16}, {"duration": 0.0, "source": 28, "betweenness": 48.0, "target": 17}, {"duration": 0.0, "source": 28, "betweenness": 48.0, "target": 18}, {"duration": 0.0, "source": 28, "betweenness": 48.0, "target": 21}, {"duration": 0.0, "source": 28, "betweenness": 48.0, "target": 22}, {"duration": 1464480.0, "source": 26, "betweenness": 68.6667, "target": 23}, {"duration": 5796900.0, "source": 29, "betweenness": 2.125, "target": 23}, {"duration": 7248900.0, "source": 31, "betweenness": 2.125, "target": 23}, {"duration": 3269100.0, "source": 23, "betweenness": 21.5917, "target": 33}, {"duration": 2757900.0, "source": 23, "betweenness": 106.725, "target": 36}, {"duration": 2669580.0, "source": 23, "betweenness": 7.05833, "target": 37}, {"duration": 2668320.0, "source": 23, "betweenness": 101.258, "target": 38}, {"duration": 0.0, "source": 23, "betweenness": 59.4917, "target": 43}, {"duration": 5465340.0, "source": 29, "betweenness": 1.625, "target": 24}, {"duration": 6917340.0, "source": 31, "betweenness": 1.625, "target": 24}, {"duration": 3600660.0, "source": 24, "betweenness": 15.5917, "target": 33}, {"duration": 3089460.0, "source": 24, "betweenness": 79.725, "target": 36}, {"duration": 3001140.0, "source": 24, "betweenness": 5.05833, "target": 37}, {"duration": 2999880.0, "source": 24, "betweenness": 75.2583, "target": 38}, {"duration": 0.0, "source": 24, "betweenness": 61.4917, "target": 43}, {"duration": 3672780.0, "source": 25, "betweenness": 19.5, "target": 36}, {"duration": 0.0, "source": 26, "betweenness": 6.41026, "target": 42}, {"duration": 0.0, "source": 26, "betweenness": 25.0769, "target": 43}, {"duration": 36117400.0, "source": 47, "betweenness": 48.0, "target": 26}, {"duration": 162720.0, "source": 28, "betweenness": 48.0, "target": 27}, {"duration": 1134600.0, "source": 36, "betweenness": 243.0, "target": 28}, {"duration": 1452000.0, "source": 31, "betweenness": 1.0, "target": 29}, {"duration": 9066000.0, "source": 29, "betweenness": 17.0436, "target": 33}, {"duration": 8554800.0, "source": 29, "betweenness": 86.6769, "target": 36}, {"duration": 8466480.0, "source": 29, "betweenness": 5.51026, "target": 37}, {"duration": 8465220.0, "source": 29, "betweenness": 81.7103, "target": 38}, {"duration": 0.0, "source": 29, "betweenness": 22.1282, "target": 42}, {"duration": 0.0, "source": 29, "betweenness": 62.7769, "target": 43}, {"duration": 1195320.0, "source": 38, "betweenness": 90.0, "target": 30}, {"duration": 10518000.0, "source": 31, "betweenness": 17.0436, "target": 33}, {"duration": 10006800.0, "source": 31, "betweenness": 86.6769, "target": 36}, {"duration": 9918480.0, "source": 31, "betweenness": 5.51026, "target": 37}, {"duration": 9917220.0, "source": 31, "betweenness": 81.7103, "target": 38}, {"duration": 0.0, "source": 31, "betweenness": 22.1282, "target": 42}, {"duration": 0.0, "source": 31, "betweenness": 62.7769, "target": 43}, {"duration": 703680.0, "source": 34, "betweenness": 48.0, "target": 32}, {"duration": 599520.0, "source": 37, "betweenness": 12.6667, "target": 33}, {"duration": 600780.0, "source": 38, "betweenness": 41.1667, "target": 33}, {"duration": 15112500.0, "source": 34, "betweenness": 87.0, "target": 36}, {"duration": 40002700.0, "source": 46, "betweenness": 7.0, "target": 34}, {"duration": 526980.0, "source": 38, "betweenness": 94.0, "target": 35}, {"duration": 603060.0, "source": 39, "betweenness": 48.0, "target": 35}, {"duration": 88320.0, "source": 37, "betweenness": 24.3333, "target": 36}, {"duration": 55115200.0, "source": 46, "betweenness": 120.0, "target": 36}, {"duration": 0.0, "source": 40, "betweenness": 48.0, "target": 43}, {"duration": 0.0, "source": 41, "betweenness": 48.0, "target": 43}, {"duration": 0.0, "source": 44, "betweenness": 48.0, "target": 43}, {"duration": 0.0, "source": 45, "betweenness": 48.0, "target": 43}, {"duration": 0.0, "source": 46, "betweenness": 48.0, "target": 48}]}